testpip_whp/__init__.py
testpip_whp/test_a.py
testpip_whp/test_t.py
test_pipinstall_whp-0.1.2.dist-info/METADATA
test_pipinstall_whp-0.1.2.dist-info/WHEEL
test_pipinstall_whp-0.1.2.dist-info/top_level.txt
test_pipinstall_whp-0.1.2.dist-info/RECORD
